s3access/__init__.py
s3access/__pkginfo__.py
s3access/reader.py
s3access/s3access.py
s3access/s3path.py
s3access/select_spec.py
s3access/sql.py
s3access/s3async/__init__.py
s3access/s3async/core.py
s3access/s3async/s3pandas.py
s3access/s3async/s3select.py
s3access/s3pandas/__init__.py
s3access/s3pandas/dataframe.py
s3access/s3pandas/reader.py
tests/__init__.py
tests/test_conditions.py
tests/test_pandas_reader.py
tests/test_s3path.py
tests/test_s3sql.py
s3access-0.9.0.dist-info/LICENSE
s3access-0.9.0.dist-info/METADATA
s3access-0.9.0.dist-info/WHEEL
s3access-0.9.0.dist-info/top_level.txt
s3access-0.9.0.dist-info/RECORD
