Metadata-Version: 2.1
Name: s3access
Version: 0.9.0
Summary: Access Parquet files in S3 via S3 Select
Home-page: https://github.com/scravy/s3access
Author: Julian Fleischer
Author-email: tirednesscankill@warhog.net
License: UNKNOWN
Platform: UNKNOWN
Classifier: Programming Language :: Python :: 3
Classifier: License :: OSI Approved :: MIT License
Classifier: Operating System :: OS Independent
Requires-Python: >=3.8
Requires-Dist: readstr (>=0.5.0)
Requires-Dist: boto3 (>=1.17.0)
Provides-Extra: async
Requires-Dist: aiobotocore (>=2.0.1) ; extra == 'async'
Provides-Extra: dev
Requires-Dist: pytest ; extra == 'dev'
Requires-Dist: readstr (>=0.5.0) ; extra == 'dev'
Requires-Dist: boto3 (>=1.17.0) ; extra == 'dev'
Requires-Dist: aiobotocore (>=2.0.1) ; extra == 'dev'
Requires-Dist: pandas (>=1.0.0) ; extra == 'dev'
Requires-Dist: pyarrow (>=3.0.0) ; extra == 'dev'
Provides-Extra: pandas
Requires-Dist: pandas (>=1.0.0) ; extra == 'pandas'
Requires-Dist: pyarrow (>=3.0.0) ; extra == 'pandas'
